{
	"name": "SpriteVisualizzatore",
	"plugin-id": "Sprite",
	"sid": 404825747901886,
	"isGlobal": false,
	"instanceVariables": [
		{
			"name": "parent",
			"type": "number",
			"desc": "",
			"sid": 964085559376337
		}
	],
	"behaviorTypes": [],
	"effectTypes": [],
	"animations": {
		"items": [
			{
				"frames": [
					{
						"width": 32,
						"height": 32,
						"originX": 0.5,
						"originY": 0.5,
						"originalSource": "",
						"exportFormat": "png",
						"exportQuality": 0.8,
						"imageSpriteId": 67,
						"useCollisionPoly": true,
						"duration": 1
					}
				],
				"sid": 574925954593458,
				"name": "Animation 1",
				"isLooping": false,
				"isPingPong": false,
				"repeatCount": 1,
				"repeatTo": 0,
				"speed": 5
			}
		],
		"subfolders": []
	}
}